[{"kind": "calendar#event", "etag": "\"3215770091688000\"", "id": "ni5vqtiuhlrus1thgu0s512614", "status": "confirmed", "htmlLink": "https://www.google.com/calendar/event?eid=bmk1dnF0aXVobHJ1czF0aGd1MHM1MTI2MTQgbXNlZ2FsQHN0dWRlbnQud2V0aGlua2NvZGUuY28uemE", "created": "2020-12-13T18:44:05.000Z", "updated": "2020-12-13T18:44:05.844Z", "summary": "msegal", "description": "bob", "creator": {"email": "msegal@student.wethinkcode.co.za", "self": true}, "organizer": {"email": "teamtwotesting@gmail.com"}, "start": {"dateTime": "2020-12-14T08:00:00+02:00"}, "end": {"dateTime": "2020-12-14T08:30:00+02:00"}, "iCalUID": "ni5vqtiuhlrus1thgu0s512614@google.com", "sequence": 0, "attendees": [{"email": "msegal@student.wethinkcode.co.za", "self": true, "responseStatus": "needsAction"}], "anyoneCanAddSelf": true, "reminders": {"useDefault": true}}, {"kind": "calendar#event", "etag": "\"3215787049440000\"", "id": "lqg6uq0g0esnv5jb0c48982ie0", "status": "confirmed", "htmlLink": "https://www.google.com/calendar/event?eid=bHFnNnVxMGcwZXNudjVqYjBjNDg5ODJpZTAgbXNlZ2FsQHN0dWRlbnQud2V0aGlua2NvZGUuY28uemE", "created": "2020-12-13T21:05:23.000Z", "updated": "2020-12-13T21:05:24.720Z", "summary": "msegal", "description": "test", "creator": {"email": "msegal@student.wethinkcode.co.za", "self": true}, "organizer": {"email": "teamtwotesting@gmail.com"}, "start": {"dateTime": "2020-12-14T13:00:00+02:00"}, "end": {"dateTime": "2020-12-14T13:30:00+02:00"}, "iCalUID": "lqg6uq0g0esnv5jb0c48982ie0@google.com", "sequence": 0, "attendees": [{"email": "msegal@student.wethinkcode.co.za", "self": true, "responseStatus": "needsAction"}], "anyoneCanAddSelf": true, "reminders": {"useDefault": true}}, {"kind": "calendar#event", "etag": "\"3215787052644000\"", "id": "c625ecbqhp5tsltgao3lf2dqoo", "status": "confirmed", "htmlLink": "https://www.google.com/calendar/event?eid=YzYyNWVjYnFocDV0c2x0Z2FvM2xmMmRxb28gbXNlZ2FsQHN0dWRlbnQud2V0aGlua2NvZGUuY28uemE", "created": "2020-12-13T21:05:24.000Z", "updated": "2020-12-13T21:05:26.322Z", "summary": "msegal", "description": "test", "creator": {"email": "msegal@student.wethinkcode.co.za", "self": true}, "organizer": {"email": "teamtwotesting@gmail.com"}, "start": {"dateTime": "2020-12-14T14:00:00+02:00"}, "end": {"dateTime": "2020-12-14T14:30:00+02:00"}, "iCalUID": "c625ecbqhp5tsltgao3lf2dqoo@google.com", "sequence": 0, "attendees": [{"email": "msegal@student.wethinkcode.co.za", "self": true, "responseStatus": "needsAction"}], "anyoneCanAddSelf": true, "reminders": {"useDefault": true}}, {"kind": "calendar#event", "etag": "\"3209988099176000\"", "id": "m8ahshl50u0cvf32v9mn8vu832_20201218T080000Z", "status": "confirmed", "htmlLink": "https://www.google.com/calendar/event?eid=bThhaHNobDUwdTBjdmYzMnY5bW44dnU4MzJfMjAyMDEyMThUMDgwMDAwWiBtc2VnYWxAc3R1ZGVudC53ZXRoaW5rY29kZS5jby56YQ", "created": "2020-10-06T13:44:38.000Z", "updated": "2020-11-10T07:40:49.588Z", "summary": "Team 2 weekly meeting", "description": "Team 2 weekly meeting.", "creator": {"email": "bmarks@student.wethinkcode.co.za"}, "organizer": {"email": "bmarks@student.wethinkcode.co.za"}, "start": {"dateTime": "2020-12-18T10:00:00+02:00", "timeZone": "Africa/Johannesburg"}, "end": {"dateTime": "2020-12-18T11:00:00+02:00", "timeZone": "Africa/Johannesburg"}, "recurringEventId": "m8ahshl50u0cvf32v9mn8vu832_R20201113T080000", "originalStartTime": {"dateTime": "2020-12-18T10:00:00+02:00", "timeZone": "Africa/Johannesburg"}, "iCalUID": "m8ahshl50u0cvf32v9mn8vu832_R20201113T080000@google.com", "sequence": 3, "attendees": [{"email": "tnjili@student.wethinkcode.co.za", "responseStatus": "needsAction"}, {"email": "anell@student.wethinkcode.co.za", "responseStatus": "needsAction"}, {"email": "epasqual@student.wethinkcode.co.za", "responseStatus": "needsAction"}, {"email": "ssamaai@student.wethinkcode.co.za", "responseStatus": "needsAction"}, {"email": "bmarks@student.wethinkcode.co.za", "organizer": true, "responseStatus": "accepted"}, {"email": "mndzawum@student.wethinkcode.co.za", "responseStatus": "needsAction"}, {"email": "bthompso@student.wethinkcode.co.za", "responseStatus": "needsAction"}, {"email": "msegal@student.wethinkcode.co.za", "self": true, "responseStatus": "accepted"}], "hangoutLink": "https://meet.google.com/udt-youb-kgn", "conferenceData": {"entryPoints": [{"entryPointType": "video", "uri": "https://meet.google.com/udt-youb-kgn", "label": "meet.google.com/udt-youb-kgn"}, {"entryPointType": "more", "uri": "https://tel.meet/udt-youb-kgn?pin=5425013081155", "pin": "5425013081155"}, {"regionCode": "ZA", "entryPointType": "phone", "uri": "tel:+27-10-823-0699", "label": "+27 10 823 0699", "pin": "699301756"}], "conferenceSolution": {"key": {"type": "hangoutsMeet"}, "name": "Google Meet", "iconUri": "https://fonts.gstatic.com/s/i/productlogos/meet_2020q4/v6/web-512dp/logo_meet_2020q4_color_2x_web_512dp.png"}, "conferenceId": "udt-youb-kgn", "signature": "AL9oL6VlZe+FM0dUpA7ovmBbX5Qk"}, "reminders": {"useDefault": true}}]